sidebar_accordion_menu/__init__.py
sidebar_accordion_menu/example.py
sidebar_accordion_menu/menu_utils.py
sidebar_accordion_menu/frontend/build/bootstrap.min.css
sidebar_accordion_menu/frontend/build/index.html
sidebar_accordion_menu/frontend/build/assets/index-BAUUQo6C.js
streamlit_sidebar_accordion_menu-0.0.2.dist-info/licenses/LICENSE
streamlit_sidebar_accordion_menu-0.0.2.dist-info/METADATA
streamlit_sidebar_accordion_menu-0.0.2.dist-info/WHEEL
streamlit_sidebar_accordion_menu-0.0.2.dist-info/top_level.txt
streamlit_sidebar_accordion_menu-0.0.2.dist-info/RECORD
