Metadata-Version: 2.4
Name: streamlit-sidebar-accordion-menu
Version: 0.0.2
Summary: A Streamlit component for creating sidebar accordion menus with navigation support
Home-page: https://github.com/gussan-me/streamlit_sidebar_accordion_menu.git
Author: Ayumu Yamaguchi
License: MIT
Project-URL: Homepage, https://github.com/gussan-me/streamlit_sidebar_accordion_menu
Project-URL: Documentation, https://github.com/gussan-me/streamlit_sidebar_accordion_menu/blob/main/README.md
Project-URL: Repository, https://github.com/gussan-me/streamlit_sidebar_accordion_menu
Project-URL: Issues, https://github.com/gussan-me/streamlit_sidebar_accordion_menu/issues
Keywords: streamlit,component,sidebar,menu,navigation,accordion
Classifier: Development Status :: 4 - Beta
Classifier: Intended Audience :: Developers
Classifier: Topic :: Software Development :: Libraries :: Python Modules
Classifier: License :: OSI Approved :: MIT License
Classifier: Programming Language :: Python :: 3
Classifier: Programming Language :: Python :: 3.8
Classifier: Programming Language :: Python :: 3.9
Classifier: Programming Language :: Python :: 3.10
Classifier: Programming Language :: Python :: 3.11
Classifier: Programming Language :: Python :: 3.12
Requires-Python: >=3.8
License-File: LICENSE
Requires-Dist: streamlit>=1.31.0
Provides-Extra: dev
Requires-Dist: wheel; extra == "dev"
Requires-Dist: pytest==7.4.0; extra == "dev"
Requires-Dist: playwright==1.48.0; extra == "dev"
Requires-Dist: requests==2.31.0; extra == "dev"
Requires-Dist: pytest-playwright-snapshot==1.0; extra == "dev"
Requires-Dist: pytest-rerunfailures==12.0; extra == "dev"
Dynamic: home-page
Dynamic: license-file
Dynamic: requires-python
